[
  {
    "money": 1206656,
    "waterlevel": 27,
    "environmentCost": 8,
    "powerPrice": 528,
    "timestamp": "2021-08-12T06:43:07.787Z",
    "turbines": [
      {
        "id": 0,
        "capasityUsage": 0.49037872621712997,
        "production": 3.881213726290376
      },
      {
        "id": 1,
        "capasityUsage": 0.14372290367441187,
        "production": 13.090906086758435
      },
      {
        "id": 2,
        "capasityUsage": 0.46789730443213573,
        "production": 2.5759967216931927
      },
      {
        "id": 3,
        "capasityUsage": 0.20530671204891537,
        "production": 17.60356239014734
      },
      {
        "id": 4,
        "capasityUsage": 0.18434685607036627,
        "production": 12.929423237680057
      },
      {
        "id": 5,
        "capasityUsage": 0.7224400246699276,
        "production": 12.096555648196187
      },
      {
        "id": 6,
        "capasityUsage": 0.5107639036543019,
        "production": 15.93518293849973
      },
      {
        "id": 7,
        "capasityUsage": 0.9060048618050334,
        "production": 15.433468903062137
      },
      {
        "id": 8,
        "capasityUsage": 0.31074660648337904,
        "production": 15.309661326323884
      },
      {
        "id": 9,
        "capasityUsage": 0.012377206951840192,
        "production": 13.84925523081957
      },
      {
        "id": 10,
        "capasityUsage": 0.9681277582384433,
        "production": 4.408559246273863
      },
      {
        "id": 11,
        "capasityUsage": 0.6485317265138713,
        "production": 18.30048374785876
      },
      {
        "id": 12,
        "capasityUsage": 0.79581862656282,
        "production": 18.90780045157005
      },
      {
        "id": 13,
        "capasityUsage": 0.20322048057031217,
        "production": 3.1018638656143622
      }
    ]
  },
  {
    "money": 899694,
    "waterlevel": 21,
    "environmentCost": 15,
    "powerPrice": 595,
    "timestamp": "2021-08-12T23:15:14.451Z",
    "turbines": [
      {
        "id": 0,
        "capasityUsage": 0.7297192164969035,
        "production": 0.5528294485912282
      },
      {
        "id": 1,
        "capasityUsage": 0.240348452202368,
        "production": 8.23816709640316
      },
      {
        "id": 2,
        "capasityUsage": 0.15387249202415498,
        "production": 17.84566927275298
      },
      {
        "id": 3,
        "capasityUsage": 0.991207933440645,
        "production": 0.12896905910906725
      },
      {
        "id": 4,
        "capasityUsage": 0.754402430428637,
        "production": 8.539385615567726
      },
      {
        "id": 5,
        "capasityUsage": 0.6645546145457457,
        "production": 10.402026915768781
      },
      {
        "id": 6,
        "capasityUsage": 0.7017270577899486,
        "production": 8.429136202350437
      },
      {
        "id": 7,
        "capasityUsage": 0.5474254144474833,
        "production": 6.274539655714214
      },
      {
        "id": 8,
        "capasityUsage": 0.004809876353958797,
        "production": 11.023700143373707
      },
      {
        "id": 9,
        "capasityUsage": 0.9966688704992157,
        "production": 2.591246585839884
      },
      {
        "id": 10,
        "capasityUsage": 0.2175989984312916,
        "production": 0.5640950161112578
      },
      {
        "id": 11,
        "capasityUsage": 0.14600416809506345,
        "production": 13.714911402331373
      },
      {
        "id": 12,
        "capasityUsage": 0.3489647902623174,
        "production": 5.672187515481894
      },
      {
        "id": 13,
        "capasityUsage": 0.4619298970875205,
        "production": 18.497448858944338
      }
    ]
  },
  {
    "money": 309997,
    "waterlevel": 32,
    "environmentCost": 29,
    "powerPrice": 393,
    "timestamp": "2021-08-12T06:51:25.098Z",
    "turbines": [
      {
        "id": 0,
        "capasityUsage": 0.4691489722815627,
        "production": 13.202050324819565
      },
      {
        "id": 1,
        "capasityUsage": 0.029808738147409253,
        "production": 7.013172008758444
      },
      {
        "id": 2,
        "capasityUsage": 0.752953389209547,
        "production": 3.874288118922424
      },
      {
        "id": 3,
        "capasityUsage": 0.33418893335543753,
        "production": 18.008377285743997
      },
      {
        "id": 4,
        "capasityUsage": 0.42345324810609286,
        "production": 2.7284008807147044
      },
      {
        "id": 5,
        "capasityUsage": 0.21639138498825283,
        "production": 16.102473891773887
      },
      {
        "id": 6,
        "capasityUsage": 0.19899650652560052,
        "production": 11.128805886391396
      },
      {
        "id": 7,
        "capasityUsage": 0.29614781879963403,
        "production": 8.259138884662024
      },
      {
        "id": 8,
        "capasityUsage": 0.589892080398444,
        "production": 8.022374100286534
      },
      {
        "id": 9,
        "capasityUsage": 0.141215974946167,
        "production": 17.744156568793862
      },
      {
        "id": 10,
        "capasityUsage": 0.6320705774730455,
        "production": 11.764536735198899
      },
      {
        "id": 11,
        "capasityUsage": 0.7477947530914573,
        "production": 3.4296708152373787
      },
      {
        "id": 12,
        "capasityUsage": 0.21442195393211527,
        "production": 6.353878977044991
      },
      {
        "id": 13,
        "capasityUsage": 0.47001300409820046,
        "production": 16.95191955822709
      }
    ]
  },
  {
    "money": 893524,
    "waterlevel": 44,
    "environmentCost": 82,
    "powerPrice": 403,
    "timestamp": "2021-08-12T08:04:15.744Z",
    "turbines": [
      {
        "id": 0,
        "capasityUsage": 0.5335624490206863,
        "production": 15.279203791920237
      },
      {
        "id": 1,
        "capasityUsage": 0.3260928910847938,
        "production": 13.366857378500658
      },
      {
        "id": 2,
        "capasityUsage": 0.7349911380189722,
        "production": 8.150881450914252
      },
      {
        "id": 3,
        "capasityUsage": 0.5550404045769648,
        "production": 7.678152682785946
      },
      {
        "id": 4,
        "capasityUsage": 0.08773616178148802,
        "production": 9.937689640776673
      },
      {
        "id": 5,
        "capasityUsage": 0.17985799703308047,
        "production": 14.696823499070867
      },
      {
        "id": 6,
        "capasityUsage": 0.549946902300019,
        "production": 13.649367248831174
      },
      {
        "id": 7,
        "capasityUsage": 0.770367308039744,
        "production": 16.09221627692811
      },
      {
        "id": 8,
        "capasityUsage": 0.18152262019259258,
        "production": 2.9531240225903788
      },
      {
        "id": 9,
        "capasityUsage": 0.35043083099213956,
        "production": 8.164226911096994
      },
      {
        "id": 10,
        "capasityUsage": 0.31879916874970204,
        "production": 12.228044881626193
      },
      {
        "id": 11,
        "capasityUsage": 0.9602037214965529,
        "production": 6.662195200259547
      },
      {
        "id": 12,
        "capasityUsage": 0.7551445670312738,
        "production": 6.855001345343568
      },
      {
        "id": 13,
        "capasityUsage": 0.5608754252972525,
        "production": 14.202272764671108
      }
    ]
  },
  {
    "money": 709569,
    "waterlevel": 41,
    "environmentCost": 23,
    "powerPrice": 441,
    "timestamp": "2021-08-12T02:37:01.964Z",
    "turbines": [
      {
        "id": 0,
        "capasityUsage": 0.4780732890836188,
        "production": 12.62320204211228
      },
      {
        "id": 1,
        "capasityUsage": 0.9944200142716109,
        "production": 6.4197539674555655
      },
      {
        "id": 2,
        "capasityUsage": 0.45699668590056386,
        "production": 3.5851491899179413
      },
      {
        "id": 3,
        "capasityUsage": 0.5081738630864174,
        "production": 14.833050269716269
      },
      {
        "id": 4,
        "capasityUsage": 0.009442895228068071,
        "production": 11.708435682339417
      },
      {
        "id": 5,
        "capasityUsage": 0.9452283780920057,
        "production": 4.514775698712256
      },
      {
        "id": 6,
        "capasityUsage": 0.13280847378374938,
        "production": 7.729288992240265
      },
      {
        "id": 7,
        "capasityUsage": 0.21062491384258797,
        "production": 4.024014987064485
      },
      {
        "id": 8,
        "capasityUsage": 0.8146655349406529,
        "production": 16.791507553769062
      },
      {
        "id": 9,
        "capasityUsage": 0.8431138668209626,
        "production": 9.25023625818499
      },
      {
        "id": 10,
        "capasityUsage": 0.033209877911314134,
        "production": 7.458192282821634
      },
      {
        "id": 11,
        "capasityUsage": 0.7499220800907245,
        "production": 4.060977453885405
      },
      {
        "id": 12,
        "capasityUsage": 0.9872741051218228,
        "production": 19.06111372984905
      },
      {
        "id": 13,
        "capasityUsage": 0.945017090552041,
        "production": 4.162498746340605
      }
    ]
  },
  {
    "money": 303881,
    "waterlevel": 44,
    "environmentCost": 4,
    "powerPrice": 611,
    "timestamp": "2021-08-12T04:41:01.596Z",
    "turbines": [
      {
        "id": 0,
        "capasityUsage": 0.4255883968200369,
        "production": 13.853812880757063
      },
      {
        "id": 1,
        "capasityUsage": 0.9858744955475949,
        "production": 0.16961457781375971
      },
      {
        "id": 2,
        "capasityUsage": 0.1915046970022507,
        "production": 17.622838076333853
      },
      {
        "id": 3,
        "capasityUsage": 0.9062982288623105,
        "production": 9.775332173744648
      },
      {
        "id": 4,
        "capasityUsage": 0.590416919343159,
        "production": 1.0029467763042206
      },
      {
        "id": 5,
        "capasityUsage": 0.4462382775011491,
        "production": 11.970774914400245
      },
      {
        "id": 6,
        "capasityUsage": 0.01977940328403993,
        "production": 1.827372096360895
      },
      {
        "id": 7,
        "capasityUsage": 0.6021363186285758,
        "production": 2.1891418625764736
      },
      {
        "id": 8,
        "capasityUsage": 0.6587034017773483,
        "production": 7.665274546339241
      },
      {
        "id": 9,
        "capasityUsage": 0.4641125521833742,
        "production": 16.599463545813848
      },
      {
        "id": 10,
        "capasityUsage": 0.41719019375117794,
        "production": 0.8716888775632173
      },
      {
        "id": 11,
        "capasityUsage": 0.5285070641456506,
        "production": 2.874406949482773
      },
      {
        "id": 12,
        "capasityUsage": 0.907801543917532,
        "production": 12.800246211305803
      },
      {
        "id": 13,
        "capasityUsage": 0.26590961431966664,
        "production": 7.808638467238595
      }
    ]
  },
  {
    "money": 1125037,
    "waterlevel": 26,
    "environmentCost": 45,
    "powerPrice": 393,
    "timestamp": "2021-08-12T07:59:13.599Z",
    "turbines": [
      {
        "id": 0,
        "capasityUsage": 0.5343805397992198,
        "production": 17.419761618345017
      },
      {
        "id": 1,
        "capasityUsage": 0.18687174934283468,
        "production": 5.7937637600227
      },
      {
        "id": 2,
        "capasityUsage": 0.6270942091056411,
        "production": 6.076317258703112
      },
      {
        "id": 3,
        "capasityUsage": 0.9762909219595588,
        "production": 10.310668717756098
      },
      {
        "id": 4,
        "capasityUsage": 0.7525003767866194,
        "production": 10.146564679327582
      },
      {
        "id": 5,
        "capasityUsage": 0.8760163614224161,
        "production": 1.6201764423214127
      },
      {
        "id": 6,
        "capasityUsage": 0.6840383287165401,
        "production": 4.49986989990032
      },
      {
        "id": 7,
        "capasityUsage": 0.580642701674343,
        "production": 5.169549571132929
      },
      {
        "id": 8,
        "capasityUsage": 0.811146541600656,
        "production": 5.800533552588284
      },
      {
        "id": 9,
        "capasityUsage": 0.0896065256172689,
        "production": 2.363476124458005
      },
      {
        "id": 10,
        "capasityUsage": 0.668665956432746,
        "production": 1.6098319831286871
      },
      {
        "id": 11,
        "capasityUsage": 0.5763130054689476,
        "production": 6.125885183310539
      },
      {
        "id": 12,
        "capasityUsage": 0.3152272190186265,
        "production": 8.155037490159227
      },
      {
        "id": 13,
        "capasityUsage": 0.36708220825576277,
        "production": 8.249141123005865
      }
    ]
  },
  {
    "money": 238750,
    "waterlevel": 40,
    "environmentCost": 85,
    "powerPrice": 416,
    "timestamp": "2021-08-12T14:40:35.849Z",
    "turbines": [
      {
        "id": 0,
        "capasityUsage": 0.9693035792745925,
        "production": 10.886870397161157
      },
      {
        "id": 1,
        "capasityUsage": 0.388110768937586,
        "production": 7.770333738687189
      },
      {
        "id": 2,
        "capasityUsage": 0.8300115245103967,
        "production": 10.539068106716758
      },
      {
        "id": 3,
        "capasityUsage": 0.4979274412013648,
        "production": 1.930851818796036
      },
      {
        "id": 4,
        "capasityUsage": 0.7580997521333099,
        "production": 10.425383540110166
      },
      {
        "id": 5,
        "capasityUsage": 0.8779320512393602,
        "production": 7.659889463665385
      },
      {
        "id": 6,
        "capasityUsage": 0.5942332809764539,
        "production": 15.76193995882747
      },
      {
        "id": 7,
        "capasityUsage": 0.042767653523519744,
        "production": 18.442791379148797
      },
      {
        "id": 8,
        "capasityUsage": 0.7079686154467446,
        "production": 6.059833437412565
      },
      {
        "id": 9,
        "capasityUsage": 0.28397515046682,
        "production": 15.849768474987325
      },
      {
        "id": 10,
        "capasityUsage": 0.15806600919796732,
        "production": 18.595921413712126
      },
      {
        "id": 11,
        "capasityUsage": 0.190697980672478,
        "production": 0.9638686207229166
      },
      {
        "id": 12,
        "capasityUsage": 0.8660142323298932,
        "production": 13.099965569256335
      },
      {
        "id": 13,
        "capasityUsage": 0.6835785943910226,
        "production": 3.0587593729002642
      }
    ]
  },
  {
    "money": 447955,
    "waterlevel": 41,
    "environmentCost": 28,
    "powerPrice": 593,
    "timestamp": "2021-08-12T11:12:55.672Z",
    "turbines": [
      {
        "id": 0,
        "capasityUsage": 0.002386751919034591,
        "production": 8.12037170307903
      },
      {
        "id": 1,
        "capasityUsage": 0.7106123907566366,
        "production": 1.9454140954594443
      },
      {
        "id": 2,
        "capasityUsage": 0.3496197526358724,
        "production": 2.957145751900759
      },
      {
        "id": 3,
        "capasityUsage": 0.0714963411305678,
        "production": 2.705171871447419
      },
      {
        "id": 4,
        "capasityUsage": 0.13184749292905007,
        "production": 8.31501933617297
      },
      {
        "id": 5,
        "capasityUsage": 0.517713385177857,
        "production": 5.849266759199403
      },
      {
        "id": 6,
        "capasityUsage": 0.7847970711810246,
        "production": 16.132924386273178
      },
      {
        "id": 7,
        "capasityUsage": 0.7947806969601048,
        "production": 10.400000682135646
      },
      {
        "id": 8,
        "capasityUsage": 0.5567760699153086,
        "production": 1.4458046520205827
      },
      {
        "id": 9,
        "capasityUsage": 0.1805080863968962,
        "production": 16.99498141795439
      },
      {
        "id": 10,
        "capasityUsage": 0.32094092821655096,
        "production": 6.162529569506271
      },
      {
        "id": 11,
        "capasityUsage": 0.7970789463082704,
        "production": 7.7304807652309755
      },
      {
        "id": 12,
        "capasityUsage": 0.24147017286657602,
        "production": 9.42047702880796
      },
      {
        "id": 13,
        "capasityUsage": 0.5210588283579087,
        "production": 14.60370233120671
      }
    ]
  },
  {
    "money": 1092969,
    "waterlevel": 40,
    "environmentCost": 96,
    "powerPrice": 590,
    "timestamp": "2021-08-12T13:11:10.121Z",
    "turbines": [
      {
        "id": 0,
        "capasityUsage": 0.770969013468604,
        "production": 14.314718325979921
      },
      {
        "id": 1,
        "capasityUsage": 0.46954423268949985,
        "production": 1.813326436913258
      },
      {
        "id": 2,
        "capasityUsage": 0.6936844630379775,
        "production": 18.713048375129244
      },
      {
        "id": 3,
        "capasityUsage": 0.25639772379348913,
        "production": 8.095403454852672
      },
      {
        "id": 4,
        "capasityUsage": 0.7071920123607371,
        "production": 1.1955873184761496
      },
      {
        "id": 5,
        "capasityUsage": 0.3173824735151709,
        "production": 4.84978551972314
      },
      {
        "id": 6,
        "capasityUsage": 0.27467973848790606,
        "production": 13.24345928323466
      },
      {
        "id": 7,
        "capasityUsage": 0.5138288029330524,
        "production": 5.583682289709559
      },
      {
        "id": 8,
        "capasityUsage": 0.8902727169607978,
        "production": 16.232595900542584
      },
      {
        "id": 9,
        "capasityUsage": 0.14308632946925326,
        "production": 9.470524167009568
      },
      {
        "id": 10,
        "capasityUsage": 0.11744513901163,
        "production": 3.8057395878300886
      },
      {
        "id": 11,
        "capasityUsage": 0.5471776231852918,
        "production": 13.590794048859598
      },
      {
        "id": 12,
        "capasityUsage": 0.7611746614371158,
        "production": 3.6319059292232874
      },
      {
        "id": 13,
        "capasityUsage": 0.9243450754053777,
        "production": 18.866702596440852
      }
    ]
  },
  {
    "money": 259321,
    "waterlevel": 40,
    "environmentCost": 91,
    "powerPrice": 539,
    "timestamp": "2021-08-12T23:54:21.429Z",
    "turbines": [
      {
        "id": 0,
        "capasityUsage": 0.3222101922325007,
        "production": 7.602966061083887
      },
      {
        "id": 1,
        "capasityUsage": 0.6355070429102618,
        "production": 1.3524100205273064
      },
      {
        "id": 2,
        "capasityUsage": 0.18231001558818138,
        "production": 5.523842857504307
      },
      {
        "id": 3,
        "capasityUsage": 0.5872260961649727,
        "production": 12.116725284919635
      },
      {
        "id": 4,
        "capasityUsage": 0.6985935683661333,
        "production": 7.6738225538507
      },
      {
        "id": 5,
        "capasityUsage": 0.7215255472653586,
        "production": 10.691214411974586
      },
      {
        "id": 6,
        "capasityUsage": 0.062209146377256275,
        "production": 7.369392750912284
      },
      {
        "id": 7,
        "capasityUsage": 0.361231294354589,
        "production": 16.30240219947568
      },
      {
        "id": 8,
        "capasityUsage": 0.1653353017931256,
        "production": 5.66104032262581
      },
      {
        "id": 9,
        "capasityUsage": 0.010126246888109591,
        "production": 12.685392899231207
      },
      {
        "id": 10,
        "capasityUsage": 0.9123482995472507,
        "production": 10.045060993460348
      },
      {
        "id": 11,
        "capasityUsage": 0.6576116029751566,
        "production": 14.116068292009903
      },
      {
        "id": 12,
        "capasityUsage": 0.6237416832932658,
        "production": 10.237092259173822
      },
      {
        "id": 13,
        "capasityUsage": 0.9407562032159065,
        "production": 11.508733899868563
      }
    ]
  },
  {
    "money": 411919,
    "waterlevel": 33,
    "environmentCost": 83,
    "powerPrice": 617,
    "timestamp": "2021-08-12T03:27:59.932Z",
    "turbines": [
      {
        "id": 0,
        "capasityUsage": 0.9388874761522852,
        "production": 3.274026487405589
      },
      {
        "id": 1,
        "capasityUsage": 0.5542000033720011,
        "production": 1.0457827569508586
      },
      {
        "id": 2,
        "capasityUsage": 0.1348259000028893,
        "production": 2.9714269024243998
      },
      {
        "id": 3,
        "capasityUsage": 0.5787671427068197,
        "production": 8.405290638427763
      },
      {
        "id": 4,
        "capasityUsage": 0.07370646994862451,
        "production": 0.45592516187650595
      },
      {
        "id": 5,
        "capasityUsage": 0.16589841754705925,
        "production": 12.78948053090001
      },
      {
        "id": 6,
        "capasityUsage": 0.6781261047923492,
        "production": 11.553682598497343
      },
      {
        "id": 7,
        "capasityUsage": 0.5482632649766979,
        "production": 3.051287554911645
      },
      {
        "id": 8,
        "capasityUsage": 0.2340657315244874,
        "production": 6.533590218628133
      },
      {
        "id": 9,
        "capasityUsage": 0.2534957100353892,
        "production": 13.23264404252849
      },
      {
        "id": 10,
        "capasityUsage": 0.32433019375172933,
        "production": 9.911899263314082
      },
      {
        "id": 11,
        "capasityUsage": 0.6549771455405311,
        "production": 6.160263833196167
      },
      {
        "id": 12,
        "capasityUsage": 0.13761680375886698,
        "production": 10.708364507565795
      },
      {
        "id": 13,
        "capasityUsage": 0.27390419157082513,
        "production": 11.371624690599004
      }
    ]
  },
  {
    "money": 138000,
    "waterlevel": 25,
    "environmentCost": 39,
    "powerPrice": 599,
    "timestamp": "2021-08-12T08:33:39.089Z",
    "turbines": [
      {
        "id": 0,
        "capasityUsage": 0.7812293601956102,
        "production": 11.163862879123883
      },
      {
        "id": 1,
        "capasityUsage": 0.3764167502177318,
        "production": 15.12838217268923
      },
      {
        "id": 2,
        "capasityUsage": 0.38002955740259514,
        "production": 14.5075896740573
      },
      {
        "id": 3,
        "capasityUsage": 0.31642634585327545,
        "production": 12.733922300215236
      },
      {
        "id": 4,
        "capasityUsage": 0.11803521685237905,
        "production": 8.013671192175686
      },
      {
        "id": 5,
        "capasityUsage": 0.6132676967545108,
        "production": 12.69251470015873
      },
      {
        "id": 6,
        "capasityUsage": 0.7710718819748308,
        "production": 4.5959833030945045
      },
      {
        "id": 7,
        "capasityUsage": 0.05859826726568507,
        "production": 0.17182772368754534
      },
      {
        "id": 8,
        "capasityUsage": 0.6965859245027133,
        "production": 7.5797411837040425
      },
      {
        "id": 9,
        "capasityUsage": 0.48482135402448523,
        "production": 11.40918017645709
      },
      {
        "id": 10,
        "capasityUsage": 0.4350794043748678,
        "production": 11.849319240809471
      },
      {
        "id": 11,
        "capasityUsage": 0.6622994849334245,
        "production": 5.445876742834081
      },
      {
        "id": 12,
        "capasityUsage": 0.48226006461362014,
        "production": 7.999290946356989
      },
      {
        "id": 13,
        "capasityUsage": 0.9082456720646865,
        "production": 6.40631766869993
      }
    ]
  },
  {
    "money": 1389304,
    "waterlevel": 30,
    "environmentCost": 60,
    "powerPrice": 433,
    "timestamp": "2021-08-12T23:05:12.791Z",
    "turbines": [
      {
        "id": 0,
        "capasityUsage": 0.5144650976288963,
        "production": 5.286469183114323
      },
      {
        "id": 1,
        "capasityUsage": 0.9977414879285211,
        "production": 18.384427318199698
      },
      {
        "id": 2,
        "capasityUsage": 0.46922379604631237,
        "production": 7.6916715276109935
      },
      {
        "id": 3,
        "capasityUsage": 0.13900793334352346,
        "production": 5.374453327819465
      },
      {
        "id": 4,
        "capasityUsage": 0.6417807927186161,
        "production": 3.546889980505154
      },
      {
        "id": 5,
        "capasityUsage": 0.40964983381506603,
        "production": 1.8811767775182844
      },
      {
        "id": 6,
        "capasityUsage": 0.9028846269482933,
        "production": 8.349805481547708
      },
      {
        "id": 7,
        "capasityUsage": 0.6968197027616088,
        "production": 15.767851723530997
      },
      {
        "id": 8,
        "capasityUsage": 0.5187070901458544,
        "production": 3.6686502257654636
      },
      {
        "id": 9,
        "capasityUsage": 0.30990181636620706,
        "production": 2.6858696000616225
      },
      {
        "id": 10,
        "capasityUsage": 0.49736578236740026,
        "production": 12.503801681903255
      },
      {
        "id": 11,
        "capasityUsage": 0.9854588319504858,
        "production": 15.934706652933741
      },
      {
        "id": 12,
        "capasityUsage": 0.27079123806686645,
        "production": 4.387197884310095
      },
      {
        "id": 13,
        "capasityUsage": 0.9517449147176242,
        "production": 14.327109742683007
      }
    ]
  },
  {
    "money": 268226,
    "waterlevel": 43,
    "environmentCost": 74,
    "powerPrice": 629,
    "timestamp": "2021-08-12T14:26:11.508Z",
    "turbines": [
      {
        "id": 0,
        "capasityUsage": 0.5443931523826517,
        "production": 9.525587911985186
      },
      {
        "id": 1,
        "capasityUsage": 0.9255063588371231,
        "production": 2.794284988714666
      },
      {
        "id": 2,
        "capasityUsage": 0.8204330680958543,
        "production": 18.48810407034796
      },
      {
        "id": 3,
        "capasityUsage": 0.6213456956241585,
        "production": 9.759184155521478
      },
      {
        "id": 4,
        "capasityUsage": 0.7016849736581487,
        "production": 11.304430097829666
      },
      {
        "id": 5,
        "capasityUsage": 0.24816415054879215,
        "production": 0.07670150729695291
      },
      {
        "id": 6,
        "capasityUsage": 0.2636407010296833,
        "production": 9.055523492400331
      },
      {
        "id": 7,
        "capasityUsage": 0.6642200327705237,
        "production": 7.6215553309138
      },
      {
        "id": 8,
        "capasityUsage": 0.44293310529140495,
        "production": 10.551687952002334
      },
      {
        "id": 9,
        "capasityUsage": 0.3338091074716407,
        "production": 12.014444865382963
      },
      {
        "id": 10,
        "capasityUsage": 0.6469634638656487,
        "production": 0.530279728390971
      },
      {
        "id": 11,
        "capasityUsage": 0.7536400108170036,
        "production": 18.040225439217757
      },
      {
        "id": 12,
        "capasityUsage": 0.21116470822251343,
        "production": 10.8046219569319
      },
      {
        "id": 13,
        "capasityUsage": 0.15663395300446203,
        "production": 11.97423399921277
      }
    ]
  },
  {
    "money": 1294906,
    "waterlevel": 32,
    "environmentCost": 91,
    "powerPrice": 460,
    "timestamp": "2021-08-12T23:52:03.262Z",
    "turbines": [
      {
        "id": 0,
        "capasityUsage": 0.6396727548345622,
        "production": 13.322962074006934
      },
      {
        "id": 1,
        "capasityUsage": 0.337553183475946,
        "production": 8.552860827142217
      },
      {
        "id": 2,
        "capasityUsage": 0.43266602561443546,
        "production": 6.239027798983771
      },
      {
        "id": 3,
        "capasityUsage": 0.04327311704528958,
        "production": 3.4722722429829225
      },
      {
        "id": 4,
        "capasityUsage": 0.616991106093411,
        "production": 12.295327013983329
      },
      {
        "id": 5,
        "capasityUsage": 0.35344879699463116,
        "production": 4.705004579355168
      },
      {
        "id": 6,
        "capasityUsage": 0.10436218190890556,
        "production": 17.867868250083802
      },
      {
        "id": 7,
        "capasityUsage": 0.6728349731458951,
        "production": 16.09257507156754
      },
      {
        "id": 8,
        "capasityUsage": 0.20781170352994982,
        "production": 15.761210039178584
      },
      {
        "id": 9,
        "capasityUsage": 0.9250525916320187,
        "production": 12.582160767272601
      },
      {
        "id": 10,
        "capasityUsage": 0.40887922787552067,
        "production": 10.996494834821986
      },
      {
        "id": 11,
        "capasityUsage": 0.7528391426424836,
        "production": 12.25688532146962
      },
      {
        "id": 12,
        "capasityUsage": 0.9108248579684759,
        "production": 11.36805619697065
      },
      {
        "id": 13,
        "capasityUsage": 0.11814803711494637,
        "production": 1.0317410479076818
      }
    ]
  },
  {
    "money": 973525,
    "waterlevel": 31,
    "environmentCost": 88,
    "powerPrice": 483,
    "timestamp": "2021-08-12T04:19:50.291Z",
    "turbines": [
      {
        "id": 0,
        "capasityUsage": 0.5926298086119177,
        "production": 8.65442004122496
      },
      {
        "id": 1,
        "capasityUsage": 0.9532793616134925,
        "production": 6.780045974023546
      },
      {
        "id": 2,
        "capasityUsage": 0.4391348386616185,
        "production": 14.818612664408288
      },
      {
        "id": 3,
        "capasityUsage": 0.4021506212061339,
        "production": 1.092439358786118
      },
      {
        "id": 4,
        "capasityUsage": 0.9526874501007927,
        "production": 16.771540393908772
      },
      {
        "id": 5,
        "capasityUsage": 0.24809436996162404,
        "production": 14.071657508325295
      },
      {
        "id": 6,
        "capasityUsage": 0.9657547502735118,
        "production": 6.326287754101973
      },
      {
        "id": 7,
        "capasityUsage": 0.8478332163453564,
        "production": 12.04278348790942
      },
      {
        "id": 8,
        "capasityUsage": 0.006081257266243201,
        "production": 4.78537374787308
      },
      {
        "id": 9,
        "capasityUsage": 0.13373602803668438,
        "production": 12.651344938568426
      },
      {
        "id": 10,
        "capasityUsage": 0.25095197549853343,
        "production": 4.929773934326226
      },
      {
        "id": 11,
        "capasityUsage": 0.7145844369614351,
        "production": 10.204447394241013
      },
      {
        "id": 12,
        "capasityUsage": 0.2709336850226902,
        "production": 8.776580623880472
      },
      {
        "id": 13,
        "capasityUsage": 0.5465365185844608,
        "production": 0.6382902367104732
      }
    ]
  },
  {
    "money": 776438,
    "waterlevel": 29,
    "environmentCost": 8,
    "powerPrice": 458,
    "timestamp": "2021-08-12T07:59:27.081Z",
    "turbines": [
      {
        "id": 0,
        "capasityUsage": 0.5223039057860492,
        "production": 15.668343629563429
      },
      {
        "id": 1,
        "capasityUsage": 0.11284837924357372,
        "production": 11.166167197941224
      },
      {
        "id": 2,
        "capasityUsage": 0.4598208665501917,
        "production": 0.47122335669958443
      },
      {
        "id": 3,
        "capasityUsage": 0.47727619253509257,
        "production": 3.758006117526006
      },
      {
        "id": 4,
        "capasityUsage": 0.3326643595161338,
        "production": 8.222371128836151
      },
      {
        "id": 5,
        "capasityUsage": 0.032341301291108016,
        "production": 18.582008552578063
      },
      {
        "id": 6,
        "capasityUsage": 0.2913351815378231,
        "production": 18.60812946929171
      },
      {
        "id": 7,
        "capasityUsage": 0.8884869494542251,
        "production": 2.348376907596488
      },
      {
        "id": 8,
        "capasityUsage": 0.9024264316109274,
        "production": 17.97211975754649
      },
      {
        "id": 9,
        "capasityUsage": 0.5083940789852566,
        "production": 16.080880020837302
      },
      {
        "id": 10,
        "capasityUsage": 0.9285071404945542,
        "production": 18.312451709223353
      },
      {
        "id": 11,
        "capasityUsage": 0.13361431842126192,
        "production": 1.2055353684484968
      },
      {
        "id": 12,
        "capasityUsage": 0.16965791708954714,
        "production": 7.649340228737475
      },
      {
        "id": 13,
        "capasityUsage": 0.804827849159478,
        "production": 9.558509155224398
      }
    ]
  },
  {
    "money": 387396,
    "waterlevel": 39,
    "environmentCost": 60,
    "powerPrice": 616,
    "timestamp": "2021-08-12T06:28:43.208Z",
    "turbines": [
      {
        "id": 0,
        "capasityUsage": 0.8857829641344941,
        "production": 9.193180507236223
      },
      {
        "id": 1,
        "capasityUsage": 0.6419753964076582,
        "production": 3.785662289215571
      },
      {
        "id": 2,
        "capasityUsage": 0.849569804590155,
        "production": 14.694152931664515
      },
      {
        "id": 3,
        "capasityUsage": 0.5289933062291132,
        "production": 2.3960626256404614
      },
      {
        "id": 4,
        "capasityUsage": 0.17021076729689755,
        "production": 7.7254940388092415
      },
      {
        "id": 5,
        "capasityUsage": 0.30399049284851576,
        "production": 1.8699743043982993
      },
      {
        "id": 6,
        "capasityUsage": 0.5894482404837293,
        "production": 6.264661505782175
      },
      {
        "id": 7,
        "capasityUsage": 0.3675314601947781,
        "production": 1.9402238550066153
      },
      {
        "id": 8,
        "capasityUsage": 0.9525712446208721,
        "production": 13.234061109791519
      },
      {
        "id": 9,
        "capasityUsage": 0.5541194264104456,
        "production": 14.059226056644421
      },
      {
        "id": 10,
        "capasityUsage": 0.14995861514835673,
        "production": 12.881716268621787
      },
      {
        "id": 11,
        "capasityUsage": 0.3708369570329315,
        "production": 16.82199684311309
      },
      {
        "id": 12,
        "capasityUsage": 0.6280746016024983,
        "production": 11.915042147665808
      },
      {
        "id": 13,
        "capasityUsage": 0.005256059022594295,
        "production": 3.4043553107882034
      }
    ]
  },
  {
    "money": 323092,
    "waterlevel": 39,
    "environmentCost": 74,
    "powerPrice": 440,
    "timestamp": "2021-08-12T11:15:08.739Z",
    "turbines": [
      {
        "id": 0,
        "capasityUsage": 0.7701232691773698,
        "production": 3.3284994115234676
      },
      {
        "id": 1,
        "capasityUsage": 0.5889727412386614,
        "production": 18.670581309342026
      },
      {
        "id": 2,
        "capasityUsage": 0.7519324573134449,
        "production": 16.022551791159
      },
      {
        "id": 3,
        "capasityUsage": 0.6910137334018045,
        "production": 4.263369434887125
      },
      {
        "id": 4,
        "capasityUsage": 0.4802739631304078,
        "production": 3.2465666253738013
      },
      {
        "id": 5,
        "capasityUsage": 0.2472182720300724,
        "production": 6.467956285443738
      },
      {
        "id": 6,
        "capasityUsage": 0.547100045535162,
        "production": 8.289837451674419
      },
      {
        "id": 7,
        "capasityUsage": 0.37049871464646067,
        "production": 12.76769902991215
      },
      {
        "id": 8,
        "capasityUsage": 0.24901946679585407,
        "production": 10.87639797279261
      },
      {
        "id": 9,
        "capasityUsage": 0.9911838994610247,
        "production": 3.415953247343277
      },
      {
        "id": 10,
        "capasityUsage": 0.9927733923497888,
        "production": 16.191362706457518
      },
      {
        "id": 11,
        "capasityUsage": 0.49287017100160324,
        "production": 2.0562401281133744
      },
      {
        "id": 12,
        "capasityUsage": 0.3347237224724744,
        "production": 15.123430768825825
      },
      {
        "id": 13,
        "capasityUsage": 0.6693108325483987,
        "production": 5.306032600755352
      }
    ]
  },
  {
    "money": 362192,
    "waterlevel": 24,
    "environmentCost": 44,
    "powerPrice": 428,
    "timestamp": "2021-08-12T10:57:07.316Z",
    "turbines": [
      {
        "id": 0,
        "capasityUsage": 0.9931504390312547,
        "production": 13.775168198867483
      },
      {
        "id": 1,
        "capasityUsage": 0.24077779390918685,
        "production": 16.510361444340028
      },
      {
        "id": 2,
        "capasityUsage": 0.07722122002033638,
        "production": 0.6330673874013102
      },
      {
        "id": 3,
        "capasityUsage": 0.027413615400365465,
        "production": 5.0942764944701535
      },
      {
        "id": 4,
        "capasityUsage": 0.26383048717055124,
        "production": 5.8562372983292335
      },
      {
        "id": 5,
        "capasityUsage": 0.101669019915553,
        "production": 14.301293299020077
      },
      {
        "id": 6,
        "capasityUsage": 0.8605830993131562,
        "production": 10.426007083399911
      },
      {
        "id": 7,
        "capasityUsage": 0.05234785541537135,
        "production": 0.04822598033900505
      },
      {
        "id": 8,
        "capasityUsage": 0.21071788704266647,
        "production": 0.4636914211613953
      },
      {
        "id": 9,
        "capasityUsage": 0.245195201864586,
        "production": 18.039457798503623
      },
      {
        "id": 10,
        "capasityUsage": 0.3729115952093591,
        "production": 10.232778842254366
      },
      {
        "id": 11,
        "capasityUsage": 0.6041371282467329,
        "production": 7.145244898924418
      },
      {
        "id": 12,
        "capasityUsage": 0.2120505333764071,
        "production": 0.24473215989045494
      },
      {
        "id": 13,
        "capasityUsage": 0.7392098955044051,
        "production": 9.600963934607332
      }
    ]
  },
  {
    "money": 1258794,
    "waterlevel": 22,
    "environmentCost": 73,
    "powerPrice": 389,
    "timestamp": "2021-08-12T06:43:31.264Z",
    "turbines": [
      {
        "id": 0,
        "capasityUsage": 0.8293464070653105,
        "production": 8.004258738027518
      },
      {
        "id": 1,
        "capasityUsage": 0.2298235092648162,
        "production": 16.082718621763874
      },
      {
        "id": 2,
        "capasityUsage": 0.6972411676594794,
        "production": 4.391358484928059
      },
      {
        "id": 3,
        "capasityUsage": 0.8018777777808896,
        "production": 3.474603429392064
      },
      {
        "id": 4,
        "capasityUsage": 0.01919282823606472,
        "production": 10.748806560690422
      },
      {
        "id": 5,
        "capasityUsage": 0.6324837311821978,
        "production": 15.055070439364572
      },
      {
        "id": 6,
        "capasityUsage": 0.6113920855549102,
        "production": 1.8504219084291478
      },
      {
        "id": 7,
        "capasityUsage": 0.9059181109256218,
        "production": 1.7510981710545668
      },
      {
        "id": 8,
        "capasityUsage": 0.290655000883538,
        "production": 11.624681977378312
      },
      {
        "id": 9,
        "capasityUsage": 0.6770256018821188,
        "production": 10.608804951271816
      },
      {
        "id": 10,
        "capasityUsage": 0.9169874271054539,
        "production": 17.241787069897715
      },
      {
        "id": 11,
        "capasityUsage": 0.7251071053258056,
        "production": 12.58863484437881
      },
      {
        "id": 12,
        "capasityUsage": 0.9802058411807273,
        "production": 5.072392984769683
      },
      {
        "id": 13,
        "capasityUsage": 0.9236849894473613,
        "production": 12.779134525043496
      }
    ]
  },
  {
    "money": 839840,
    "waterlevel": 42,
    "environmentCost": 16,
    "powerPrice": 458,
    "timestamp": "2021-08-12T13:25:36.366Z",
    "turbines": [
      {
        "id": 0,
        "capasityUsage": 0.42725990194636565,
        "production": 2.395856006330426
      },
      {
        "id": 1,
        "capasityUsage": 0.5933184414082533,
        "production": 9.278664551478325
      },
      {
        "id": 2,
        "capasityUsage": 0.02280639013428898,
        "production": 16.93194141973605
      },
      {
        "id": 3,
        "capasityUsage": 0.7652328125045735,
        "production": 13.36595803215488
      },
      {
        "id": 4,
        "capasityUsage": 0.3568512994318418,
        "production": 1.74236491553195
      },
      {
        "id": 5,
        "capasityUsage": 0.9564712432653433,
        "production": 9.558484564720775
      },
      {
        "id": 6,
        "capasityUsage": 0.6359791610692918,
        "production": 19.020923321152917
      },
      {
        "id": 7,
        "capasityUsage": 0.11344113489004726,
        "production": 9.296533106095472
      },
      {
        "id": 8,
        "capasityUsage": 0.0831271757965768,
        "production": 17.375673595404947
      },
      {
        "id": 9,
        "capasityUsage": 0.0877697235267787,
        "production": 3.2004132396373173
      },
      {
        "id": 10,
        "capasityUsage": 0.20575280445145183,
        "production": 7.904983221341401
      },
      {
        "id": 11,
        "capasityUsage": 0.40469749973944613,
        "production": 16.741497252574298
      },
      {
        "id": 12,
        "capasityUsage": 0.4603307262465093,
        "production": 16.805019382733196
      },
      {
        "id": 13,
        "capasityUsage": 0.2760910845076763,
        "production": 15.317507331853074
      }
    ]
  },
  {
    "money": 650465,
    "waterlevel": 31,
    "environmentCost": 34,
    "powerPrice": 514,
    "timestamp": "2021-08-12T09:15:54.370Z",
    "turbines": [
      {
        "id": 0,
        "capasityUsage": 0.8533123733571297,
        "production": 15.342855584130438
      },
      {
        "id": 1,
        "capasityUsage": 0.6739117986278433,
        "production": 2.995478583272331
      },
      {
        "id": 2,
        "capasityUsage": 0.7592916335903386,
        "production": 8.4392836313522
      },
      {
        "id": 3,
        "capasityUsage": 0.29871912145836155,
        "production": 12.973735573344882
      },
      {
        "id": 4,
        "capasityUsage": 0.9810593699237449,
        "production": 7.091431216438778
      },
      {
        "id": 5,
        "capasityUsage": 0.5484604945565899,
        "production": 1.0980915605979846
      },
      {
        "id": 6,
        "capasityUsage": 0.0959703502098801,
        "production": 1.046409991189054
      },
      {
        "id": 7,
        "capasityUsage": 0.7439855437300336,
        "production": 5.1308051776265025
      },
      {
        "id": 8,
        "capasityUsage": 0.9754899160407715,
        "production": 14.695442437803145
      },
      {
        "id": 9,
        "capasityUsage": 0.9986824165576813,
        "production": 5.4742934466987325
      },
      {
        "id": 10,
        "capasityUsage": 0.915623356758386,
        "production": 18.838918825646036
      },
      {
        "id": 11,
        "capasityUsage": 0.0377533474610563,
        "production": 6.303012287306261
      },
      {
        "id": 12,
        "capasityUsage": 0.5081479277293808,
        "production": 12.744376663198079
      },
      {
        "id": 13,
        "capasityUsage": 0.6724012516011284,
        "production": 13.681840044753146
      }
    ]
  }
]
